zram_advisor/__init__.py
zram_advisor/fix-zram.sh
zram_advisor/main.py
zram_advisor/random-sites.txt
zram_advisor-1.1.2.dist-info/entry_points.txt
zram_advisor-1.1.2.dist-info/licenses/LICENSE
zram_advisor-1.1.2.dist-info/WHEEL
zram_advisor-1.1.2.dist-info/METADATA
zram_advisor-1.1.2.dist-info/RECORD
