Metadata-Version: 2.4
Name: zram-advisor
Version: 1.1.2
Summary: zRAM status and setup tools
Keywords: zram,zram service
Author-email: Joe Defen <joedef@duck.com>
Requires-Python: >=3.8
Classifier: Programming Language :: Python :: 3
Classifier: License :: OSI Approved :: MIT License
Classifier: Operating System :: POSIX :: Linux
License-File: LICENSE
Project-URL: Bug Tracker, https://github.com/joedefen/zram-advisor/issues
Project-URL: Homepage, https://github.com/joedefen/zram-advisor
